pyrekit/__init__.py
pyrekit/cli.py
pyrekit/files.py
pyrekit/handlers.py
pyrekit/server.py
pyrekit-0.1.19.dist-info/METADATA
pyrekit-0.1.19.dist-info/WHEEL
pyrekit-0.1.19.dist-info/entry_points.txt
pyrekit-0.1.19.dist-info/top_level.txt
pyrekit-0.1.19.dist-info/RECORD
