Metadata-Version: 2.4
Name: pyrekit
Version: 0.1.19
Summary: A toolkit to create react apps with python backend and includes pywebview to make desktop apps.
Author-email: TuTheWeeb <eduardo.tuler@gmail.com>
Project-URL: Homepage, https://github.com/TuTheWeeb/pyrekit
Project-URL: Repository, https://github.com/TuTheWeeb/pyrekit
Classifier: Programming Language :: Python :: 3
Classifier: License :: OSI Approved :: MIT License
Classifier: Operating System :: OS Independent
Requires-Python: >=3.10
Requires-Dist: beautifulsoup4>=4.12.0
Requires-Dist: Flask>=2.3.0
Requires-Dist: Flask-Cors>=4.0.0
Requires-Dist: watchdog>=3.0.0
Requires-Dist: pywebview>=4.0.0
Requires-Dist: requests
Requires-Dist: pillow
Requires-Dist: uvicorn
Requires-Dist: asgiref
